AUTHORS
LICENSE
MANIFEST.in
README.rst
setup.py
django_gears/__init__.py
django_gears/finders.py
django_gears/handlers.py
django_gears/settings.py
django_gears/urls.py
django_gears/utils.py
django_gears/views.py
django_gears.egg-info/PKG-INFO
django_gears.egg-info/SOURCES.txt
django_gears.egg-info/dependency_links.txt
django_gears.egg-info/requires.txt
django_gears.egg-info/top_level.txt
django_gears/management/__init__.py
django_gears/management/commands/__init__.py
django_gears/management/commands/collectassets.py
django_gears/management/commands/runserver.py
django_gears/templatetags/__init__.py
django_gears/templatetags/gears.py