Metadata-Version: 1.1
Name: django-gears
Version: 0.7.1
Summary: Compiles and concatenates JavaScript and CSS assets.
Home-page: https://github.com/gears/django-gears
Author: Mike Yumatov
Author-email: mike@yumatov.org
License: ISC
Platform: UNKNOWN
Classifier: Development Status :: 3 - Alpha
Classifier: Framework :: Django
Classifier: Intended Audience :: Developers
Classifier: License :: OSI Approved :: ISC License (ISCL)
Classifier: Operating System :: OS Independent
Classifier: Programming Language :: Python
Classifier: Programming Language :: Python :: 2.6
Classifier: Programming Language :: Python :: 2.7
Classifier: Topic :: Internet :: WWW/HTTP
